inkline/__init__.py
inkline/art.py
inkline/info.py
inkline/py.typed
inkline/renderer.py
inkline/token.py
inkline/tokenizer.py
inkline-1.0.4.dist-info/METADATA
inkline-1.0.4.dist-info/WHEEL
inkline-1.0.4.dist-info/top_level.txt
inkline-1.0.4.dist-info/RECORD
