Metadata-Version: 2.4
Name: inkline
Version: 1.0.4
Summary: Advanced ASCII Art rendering library with color support
Author-email: CELESTIFYX Team <celestifyx@gmail.com>
License-Expression: GPL-3.0-or-later
Project-URL: Homepage, https://gitlab.com/inkline/inkline-py
Project-URL: Repository, https://gitlab.com/inkline/inkline-py
Project-URL: Issues, https://gitlab.com/inkline/inkline-py/-/issues
Keywords: ascii,art,terminal,colors,ansi,rendering
Classifier: Programming Language :: Python :: 3.12
Classifier: Programming Language :: Python :: 3.13
Classifier: Topic :: Software Development :: Libraries :: Python Modules
Classifier: Topic :: Multimedia :: Graphics
Classifier: Operating System :: OS Independent
Requires-Python: >=3.12
Requires-Dist: chromakitx>=1.0.4
